fakecbed/__init__.py
fakecbed/discretized.py
fakecbed/shapes.py
fakecbed/tds.py
fakecbed/version.py
fakecbed-0.5.3.dist-info/licenses/LICENSE
fakecbed-0.5.3.dist-info/METADATA
fakecbed-0.5.3.dist-info/WHEEL
fakecbed-0.5.3.dist-info/top_level.txt
fakecbed-0.5.3.dist-info/RECORD
