Metadata-Version: 2.4
Name: fakecbed
Version: 0.5.3
Summary: A Python library for generating quickly images that imitate convergent beam electron diffraction patterns.
Author-email: Matthew Fitzpatrick <matthew.rc.fitzpatrick@gmail.com>
Project-URL: Homepage, https://mrfitzpa.github.io/fakecbed
Project-URL: Repository, https://github.com/mrfitzpa/fakecbed
Keywords: pytorch,microscopy,diffraction,cbed
Classifier: License :: OSI Approved :: GNU General Public License v3 (GPLv3)
Classifier: Development Status :: 5 - Production/Stable
Classifier: Intended Audience :: Science/Research
Classifier: Programming Language :: Python
Classifier: Programming Language :: Python :: 3
Classifier: Programming Language :: Python :: 3.8
Classifier: Programming Language :: Python :: 3.9
Classifier: Programming Language :: Python :: 3.10
Classifier: Programming Language :: Python :: 3.11
Classifier: Programming Language :: Python :: 3.12
Classifier: Operating System :: OS Independent
Classifier: Natural Language :: English
Requires-Python: >=3.8
License-File: LICENSE
Requires-Dist: distoptica>=0.4.0
Requires-Dist: empix>=0.0.6
Provides-Extra: tests
Requires-Dist: pytest-cov; extra == "tests"
Provides-Extra: examples
Requires-Dist: jupyter; extra == "examples"
Requires-Dist: ipympl; extra == "examples"
Provides-Extra: docs
Requires-Dist: sphinx<7; extra == "docs"
Requires-Dist: sphinx_rtd_theme; extra == "docs"
Requires-Dist: sphinx-autodoc-typehints; extra == "docs"
Requires-Dist: numpydoc; extra == "docs"
Requires-Dist: docutils; extra == "docs"
Provides-Extra: all
Requires-Dist: fakecbed[docs,examples,tests]; extra == "all"
Dynamic: license-file
